docent/__init__.py
docent/core/__init__.py
docent/core/constants.py
docent/core/exceptions.py
docent/core/logger.py
docent/core/objects.py
docent/core/patterns.py
docent/core/types.py
docent/core/utils.py
docent/docs/__init__.py
docent/docs/commands/__init__.py
docent/docs/static/__init__.py
docent/docs/static/conf.tpl
docent/docs/static/favicon.ico
docent/docs/static/logo.png
docent/rest/__init__.py
docent/rest/api.py
docent/rest/constants.py
docent/rest/exceptions.py
docent/rest/handler.py
docent/rest/resource.py
docent/rest/utils.py
docent/rest/commands/__init__.py
docent/rest/enums/__init__.py
docent/rest/enums/component.py
docent/rest/enums/header.py
docent/rest/enums/parameter.py
docent/rest/enums/schema.py
docent/rest/enums/security.py
docent/rest/healthz/__init__.py
docent/rest/healthz/constants.py
docent/rest/healthz/get.py
docent/rest/healthz/resource.py
docent/rest/objects/__init__.py
docent/rest/objects/base.py
docent/rest/objects/constants.py
docent/rest/objects/documentation.py
docent/rest/objects/method.py
docent/rest/objects/parameter.py
docent/rest/objects/path.py
docent/rest/objects/request.py
docent/rest/objects/response.py
docent/rest/objects/schema.py
docent/rest/objects/security.py
docent/rest/objects/validator.py
docent/rest/static/__init__.py
docent/rest/static/favicon-16x16.png
docent/rest/static/favicon-32x32.png
docent/rest/static/favicon.ico
docent/rest/static/swagger.html
docent/template/__init__.py
docent/template/api/__init__.py
docent/template/api/apis/__init__.py
docent/template/api/apis/constants.py
docent/template/api/apis/v1/__init__.py
docent/template/api/apis/v1/constants.py
docent/template/api/apis/v1/pets/__init__.py
docent/template/api/apis/v1/pets/constants.py
docent/template/api/apis/v1/pets/delete.py
docent/template/api/apis/v1/pets/get.py
docent/template/api/apis/v1/pets/patch.py
docent/template/api/apis/v1/pets/post.py
docent/template/api/apis/v1/pets/put.py
docent/template/api/apis/v1/pets/resource.py
docent-0.0.1a14.dist-info/LICENSE
docent-0.0.1a14.dist-info/METADATA
docent-0.0.1a14.dist-info/WHEEL
docent-0.0.1a14.dist-info/entry_points.txt
docent-0.0.1a14.dist-info/top_level.txt
docent-0.0.1a14.dist-info/RECORD
